<?xml version="1.0" encoding="utf-8"?>
<openerp>
<data>
    <record model="ir.ui.view" id="view_picking_form">
        <field name="name">stock.picking.inherit</field>
        <field name="model">stock.picking</field>
        <field name="inherit_id" ref="stock.view_picking_form"/>
        <field name="arch" type="xml">
            <button name="action_cancel" position="after">
                <button name="generate_logistic_despatch" state="done" string="Generate Despatch" type="object"/>
            </button>
            <field name="partner_id" position="after">
                <field name="expedition_id" />
                <field name="despatch_id" />
            </field>
        </field>
    </record>
</data>
</openerp>
