<?xml version="1.0" encoding="utf-8"?>
<odoo>
    <record id="res_config_settings_view_form" model="ir.ui.view">
        <field name="name">res.config.settings.view.form.inherit.einvoice</field>
        <field name="model">res.config.settings</field>
        <field name="inherit_id" ref="account.res_config_settings_view_form"/>
        <field name="arch" type="xml">
            <xpath expr="//div[@id='invoicing_settings']" position="after">
                <h2>Diario de detracci칩n</h2>
                <div class="row mt16 o_settings_container" name="rucsearch_setting_container">
                    <div class="col-12 col-lg-6 o_setting_box" id="detraction_journal">
                        <div class="o_setting_left_pane">
                            <!-- <field name="detraction_journal_id"/> -->
                        </div>
                        <div class="o_setting_right_pane">
                            <label for="detraction_journal_id"/>
                            <span class="fa fa-lg fa-building-o" title="Diario de detracci칩n." groups="account.group_account_user"/>
                            <div class="text-muted">Diario en el cual se reconocer치 como de detracci칩n</div>
                            <field name="detraction_journal_id"/>
                        </div>
                    </div>
                </div>
            </xpath>
        </field>
    </record>
</odoo>